tax2peptide/Accession.py
tax2peptide/DatabaseCleaner.py
tax2peptide/Download.py
tax2peptide/Output.py
tax2peptide/TaxonGraph.py
tax2peptide/TestFile.py
tax2peptide/WriteCustomDB.py
tax2peptide/__init__.py
tax2peptide/__main__.py
tax2peptide/version.py
tax2peptide-0.0.21.dist-info/LICENSE
tax2peptide-0.0.21.dist-info/METADATA
tax2peptide-0.0.21.dist-info/WHEEL
tax2peptide-0.0.21.dist-info/top_level.txt
tax2peptide-0.0.21.dist-info/RECORD
