Metadata-Version: 2.1
Name: tax2peptide
Version: 0.0.21
Summary: tax2peptide creates based on given taxon IDs and a reference database a taxon specific database in fasta format.
Home-page: https://github.com/jschmacht/tax2peptide
Author: Juliane Schmachtenberg
Author-email: jule-schmachtenberg@web.de
License: UNKNOWN
Platform: UNKNOWN
Classifier: Programming Language :: Python :: 3
Classifier: License :: OSI Approved :: MIT License
Classifier: Operating System :: OS Independent
Requires-Python: ~=3.6
Requires-Dist: biopython
Requires-Dist: tqdm
Requires-Dist: wget
